deux/__init__.py
deux/abstract_models.py
deux/app_settings.py
deux/constants.py
deux/exceptions.py
deux/models.py
deux/notifications.py
deux/serializers.py
deux/services.py
deux/strings.py
deux/urls.py
deux/validators.py
deux/views.py
deux/authtoken/__init__.py
deux/authtoken/serializers.py
deux/authtoken/urls.py
deux/authtoken/views.py
deux/authtoken/tests/__init__.py
deux/authtoken/tests/test_serializers.py
deux/authtoken/tests/test_views.py
deux/migrations/0001_initial.py
deux/migrations/__init__.py
deux/oauth2/__init__.py
deux/oauth2/backends.py
deux/oauth2/exceptions.py
deux/oauth2/urls.py
deux/oauth2/validators.py
deux/oauth2/views.py
deux/oauth2/tests/__init__.py
deux/oauth2/tests/test_authentication.py
deux/tests/__init__.py
deux/tests/test_base.py
deux/tests/test_models.py
deux/tests/test_notifications.py
deux/tests/test_services.py
deux/tests/test_validators.py
deux/tests/test_views.py
deux-1.2.0.dist-info/DESCRIPTION.rst
deux-1.2.0.dist-info/METADATA
deux-1.2.0.dist-info/RECORD
deux-1.2.0.dist-info/WHEEL
deux-1.2.0.dist-info/metadata.json
deux-1.2.0.dist-info/top_level.txt
test_proj/__init__.py
test_proj/settings.py
test_proj/urls.py
test_proj/wsgi.py
